<annotation>
	<folder>smoke</folder>
	<filename>290.jpg</filename>
	<path>E:\Project\label\smoke\290.jpg</path>
	<source>
		<database>Unknown</database>
	</source>
	<size>
		<width>500</width>
		<height>333</height>
		<depth>3</depth>
	</size>
	<segmented>0</segmented>
	<object>
		<name>smoke</name>
		<pose>Unspecified</pose>
		<truncated>1</truncated>
		<difficult>0</difficult>
		<bndbox>
			<xmin>1</xmin>
			<ymin>7</ymin>
			<xmax>500</xmax>
			<ymax>151</ymax>
		</bndbox>
	</object>
</annotation>
