<annotation>
	<folder>smoke</folder>
	<filename>927.jpg</filename>
	<path>E:\Project\label\smoke\927.jpg</path>
	<source>
		<database>Unknown</database>
	</source>
	<size>
		<width>500</width>
		<height>308</height>
		<depth>3</depth>
	</size>
	<segmented>0</segmented>
	<object>
		<name>fire</name>
		<pose>Unspecified</pose>
		<truncated>0</truncated>
		<difficult>0</difficult>
		<bndbox>
			<xmin>25</xmin>
			<ymin>166</ymin>
			<xmax>322</xmax>
			<ymax>279</ymax>
		</bndbox>
	</object>
	<object>
		<name>smoke</name>
		<pose>Unspecified</pose>
		<truncated>0</truncated>
		<difficult>0</difficult>
		<bndbox>
			<xmin>74</xmin>
			<ymin>8</ymin>
			<xmax>433</xmax>
			<ymax>140</ymax>
		</bndbox>
	</object>
</annotation>
