<annotation>
	<folder>smoke</folder>
	<filename>940.jpg</filename>
	<path>E:\Project\label\smoke\940.jpg</path>
	<source>
		<database>Unknown</database>
	</source>
	<size>
		<width>500</width>
		<height>332</height>
		<depth>3</depth>
	</size>
	<segmented>0</segmented>
	<object>
		<name>fire</name>
		<pose>Unspecified</pose>
		<truncated>1</truncated>
		<difficult>0</difficult>
		<bndbox>
			<xmin>5</xmin>
			<ymin>215</ymin>
			<xmax>500</xmax>
			<ymax>257</ymax>
		</bndbox>
	</object>
	<object>
		<name>smoke</name>
		<pose>Unspecified</pose>
		<truncated>0</truncated>
		<difficult>0</difficult>
		<bndbox>
			<xmin>5</xmin>
			<ymin>42</ymin>
			<xmax>499</xmax>
			<ymax>207</ymax>
		</bndbox>
	</object>
</annotation>
