<?xml version="1.0" ?><annotation>
  <folder>fire-douyin</folder>
  <filename>douyin(99)</filename>
  <path>douyin(99)</path>
  <source>
    <database>Unknown</database>
  </source>
  <size>
    <width>720</width>
    <height>1280</height>
    <depth>3</depth>
  </size>
  <segmented>0</segmented>
  <object>
    <name>fire</name>
    <pose>Unspecified</pose>
    <truncated>0</truncated>
    <difficult>0</difficult>
    <bndbox>
      <xmin>86</xmin>
      <ymin>216</ymin>
      <xmax>686</xmax>
      <ymax>1094</ymax>
    </bndbox>
  </object>
</annotation>