<?xml version="1.0" ?><annotation>
  <folder>JPEGImages</folder>
  <filename>fire_shouji(43)</filename>
  <path>C:\Users\HYZ\Desktop\VOC2007\JPEGImages\fire_shouji(43).jpg</path>
  <source>
    <database>Unknown</database>
  </source>
  <size>
    <width>725</width>
    <height>544</height>
    <depth>3</depth>
  </size>
  <segmented>0</segmented>
  <object>
    <name>fire</name>
    <pose>Unspecified</pose>
    <truncated>0</truncated>
    <difficult>0</difficult>
    <bndbox>
      <xmin>1</xmin>
      <ymin>67</ymin>
      <xmax>264</xmax>
      <ymax>344</ymax>
    </bndbox>
  </object>
  <object>
    <name>yanwu</name>
    <pose>Unspecified</pose>
    <truncated>0</truncated>
    <difficult>0</difficult>
    <bndbox>
      <xmin>294</xmin>
      <ymin>21</ymin>
      <xmax>631</xmax>
      <ymax>397</ymax>
    </bndbox>
  </object>
</annotation>