<?xml version="1.0" ?><annotation>
	<folder>fire&amp;smoke</folder>
	<filename>internet(4503)</filename>
	<path>C:\Users\86377\Desktop\fire&amp;smoke\internet(4503).jpg</path>
	<source>
		<database>Unknown</database>
	</source>
	<size>
		<width>500</width>
		<height>338</height>
		<depth>3</depth>
	</size>
	<segmented>0</segmented>
	<object>
		<name>fire</name>
		<pose>Unspecified</pose>
		<truncated>1</truncated>
		<difficult>0</difficult>
		<bndbox>
			<xmin>37</xmin>
			<ymin>166</ymin>
			<xmax>500</xmax>
			<ymax>282</ymax>
		</bndbox>
	</object>
</annotation>