<?xml version="1.0" ?><annotation>
	<folder>fire&amp;smoke</folder>
	<filename>internet(1235)</filename>
	<path>C:\Users\86377\Desktop\fire&amp;smoke\internet(1235).jpg</path>
	<source>
		<database>Unknown</database>
	</source>
	<size>
		<width>370</width>
		<height>245</height>
		<depth>3</depth>
	</size>
	<segmented>0</segmented>
	<object>
		<name>fire</name>
		<pose>Unspecified</pose>
		<truncated>0</truncated>
		<difficult>0</difficult>
		<bndbox>
			<xmin>255</xmin>
			<ymin>136</ymin>
			<xmax>280</xmax>
			<ymax>180</ymax>
		</bndbox>
	</object>
</annotation>