<?xml version="1.0" ?><annotation>
  <folder>JPEGImages</folder>
  <filename>internet(347)</filename>
  <path>C:\Users\HYZ\Desktop\VOC2007\JPEGImages\internet(347).jpg</path>
  <source>
    <database>Unknown</database>
  </source>
  <size>
    <width>500</width>
    <height>339</height>
    <depth>3</depth>
  </size>
  <segmented>0</segmented>
  <object>
    <name>fire</name>
    <pose>Unspecified</pose>
    <truncated>0</truncated>
    <difficult>0</difficult>
    <bndbox>
      <xmin>288</xmin>
      <ymin>21</ymin>
      <xmax>392</xmax>
      <ymax>134</ymax>
    </bndbox>
  </object>
  <object>
    <name>yanwu</name>
    <pose>Unspecified</pose>
    <truncated>0</truncated>
    <difficult>0</difficult>
    <bndbox>
      <xmin>87</xmin>
      <ymin>5</ymin>
      <xmax>282</xmax>
      <ymax>151</ymax>
    </bndbox>
  </object>
  <object>
    <name>fire</name>
    <pose>Unspecified</pose>
    <truncated>0</truncated>
    <difficult>0</difficult>
    <bndbox>
      <xmin>3</xmin>
      <ymin>55</ymin>
      <xmax>97</xmax>
      <ymax>213</ymax>
    </bndbox>
  </object>
</annotation>