<?xml version="1.0" ?><annotation>
	<folder>fire&amp;smoke</folder>
	<filename>internet(1519)</filename>
	<path>C:\Users\86377\Desktop\fire&amp;smoke\internet(1519).jpg</path>
	<source>
		<database>Unknown</database>
	</source>
	<size>
		<width>480</width>
		<height>280</height>
		<depth>3</depth>
	</size>
	<segmented>0</segmented>
	<object>
		<name>fire</name>
		<pose>Unspecified</pose>
		<truncated>0</truncated>
		<difficult>0</difficult>
		<bndbox>
			<xmin>55</xmin>
			<ymin>92</ymin>
			<xmax>116</xmax>
			<ymax>172</ymax>
		</bndbox>
	</object>
	<object>
		<name>fire</name>
		<pose>Unspecified</pose>
		<truncated>0</truncated>
		<difficult>0</difficult>
		<bndbox>
			<xmin>122</xmin>
			<ymin>123</ymin>
			<xmax>277</xmax>
			<ymax>166</ymax>
		</bndbox>
	</object>
	<object>
		<name>fire</name>
		<pose>Unspecified</pose>
		<truncated>0</truncated>
		<difficult>0</difficult>
		<bndbox>
			<xmin>342</xmin>
			<ymin>93</ymin>
			<xmax>408</xmax>
			<ymax>197</ymax>
		</bndbox>
	</object>
</annotation>