<annotation>
	<folder>FireData</folder>
	<filename>Fire_9893.jpg</filename>
	<source>
		<database>The VOC2005 Database</database>
		<annotation>PASCAL VOC2005</annotation>
		<image>flickr</image>
	</source>
	<size>
		<width>1048</width>
		<height>744</height>
		<depth>3</depth>
	</size>
	<segmented>0</segmented>
	<object>
		<name>fire</name>
		<pose>Unspecified</pose>
		<truncated>0</truncated>
		<difficult>0</difficult>
		<bndbox>
			<xmin>755</xmin>
			<ymin>473</ymin>
			<xmax>895</xmax>
			<ymax>600</ymax>
		</bndbox>
	</object>
</annotation>