<?xml version="1.0" ?><annotation>
  <folder>JPEGImages</folder>
  <filename>1577195120.4639676</filename>
  <path>C:\Users\Administrator\Desktop\VOCdevkit\VOC2007\JPEGImages\1577195120.4639676.jpg</path>
  <source>
    <database>Unknown</database>
  </source>
  <size>
    <width>544</width>
    <height>960</height>
    <depth>3</depth>
  </size>
  <segmented>0</segmented>
  <object>
    <name>fire</name>
    <pose>Unspecified</pose>
    <truncated>0</truncated>
    <difficult>0</difficult>
    <bndbox>
      <xmin>222</xmin>
      <ymin>218</ymin>
      <xmax>390</xmax>
      <ymax>328</ymax>
    </bndbox>
  </object>
</annotation>