<?xml version="1.0" ?><annotation>
  <folder>JPEGImages</folder>
  <filename>internet(6022)</filename>
  <path>C:\Users\HYZ\Desktop\VOC2007\JPEGImages\internet(6022).jpg</path>
  <source>
    <database>Unknown</database>
  </source>
  <size>
    <width>499</width>
    <height>329</height>
    <depth>3</depth>
  </size>
  <segmented>0</segmented>
  <object>
    <name>fire</name>
    <pose>Unspecified</pose>
    <truncated>0</truncated>
    <difficult>0</difficult>
    <bndbox>
      <xmin>250</xmin>
      <ymin>43</ymin>
      <xmax>298</xmax>
      <ymax>140</ymax>
    </bndbox>
  </object>
  <object>
    <name>fire</name>
    <pose>Unspecified</pose>
    <truncated>0</truncated>
    <difficult>0</difficult>
    <bndbox>
      <xmin>118</xmin>
      <ymin>53</ymin>
      <xmax>177</xmax>
      <ymax>174</ymax>
    </bndbox>
  </object>
  <object>
    <name>fire</name>
    <pose>Unspecified</pose>
    <truncated>0</truncated>
    <difficult>0</difficult>
    <bndbox>
      <xmin>33</xmin>
      <ymin>144</ymin>
      <xmax>85</xmax>
      <ymax>215</ymax>
    </bndbox>
  </object>
</annotation>