<?xml version='1.0' encoding='utf-8'?>
<annotation>
	<folder>cutted</folder>
	<filename>a(1346).jpg</filename>
	<path>./Annotations/a(1346).jpg</path>
	<source>
		<database>Unknown</database>
	</source>
	<size>
		<width>320</width>
		<height>240</height>
		<depth>3</depth>
	</size>
	<segmented>0</segmented>
	<object>
		<name>fire</name>
		<pose>Unspecified</pose>
		<truncated>0</truncated>
		<difficult>0</difficult>
		<bndbox>
			<xmin>92</xmin>
			<ymin>142</ymin>
			<xmax>158</xmax>
			<ymax>198</ymax>
		</bndbox>
	</object>
	<object>
		<name>fire</name>
		<pose>Unspecified</pose>
		<truncated>0</truncated>
		<difficult>0</difficult>
		<bndbox>
			<xmin>252</xmin>
			<ymin>50</ymin>
			<xmax>315</xmax>
			<ymax>181</ymax>
		</bndbox>
	</object>
	<object>
		<name>fire</name>
		<pose>Unspecified</pose>
		<truncated>0</truncated>
		<difficult>0</difficult>
		<bndbox>
			<xmin>175</xmin>
			<ymin>75</ymin>
			<xmax>222</xmax>
			<ymax>176</ymax>
		</bndbox>
	</object>
</annotation>