<?xml version='1.0' encoding='utf-8'?>
<annotation>
  <folder>JPEGImages</folder>
  <filename>b(13).jpg</filename>
  <path>./Annotations/b(13).jpg</path>
  <source>
    <database>Unknown</database>
  </source>
  <size>
    <width>1440</width>
    <height>1080</height>
    <depth>3</depth>
  </size>
  <segmented>0</segmented>
  <object>
    <name>smoke</name>
    <pose>Unspecified</pose>
    <truncated>0</truncated>
    <difficult>0</difficult>
    <bndbox>
      <xmin>588</xmin>
      <ymin>539</ymin>
      <xmax>950</xmax>
      <ymax>803</ymax>
    </bndbox>
  </object>
</annotation>