<?xml version='1.0' encoding='utf-8'?>
<annotation>
	<folder>image</folder>
	<filename>c(702).jpg</filename>
	<path>./Annotations/c(702).jpg</path>
	<source>
		<database>Unknown</database>
	</source>
	<size>
		<width>320</width>
		<height>240</height>
		<depth>3</depth>
	</size>
	<segmented>0</segmented>
	<object>
		<name>smoke</name>
		<pose>Unspecified</pose>
		<truncated>0</truncated>
		<difficult>0</difficult>
		<bndbox>
			<xmin>94</xmin>
			<ymin>57</ymin>
			<xmax>139</xmax>
			<ymax>141</ymax>
		</bndbox>
	</object>
	<object>
		<name>smoke</name>
		<pose>Unspecified</pose>
		<truncated>0</truncated>
		<difficult>0</difficult>
		<bndbox>
			<xmin>172</xmin>
			<ymin>79</ymin>
			<xmax>209</xmax>
			<ymax>139</ymax>
		</bndbox>
	</object>
</annotation>