<?xml version='1.0' encoding='utf-8'?>
<annotation>
  <folder>images</folder>
  <filename>e(1359).jpg</filename>
  <path>./Annotations/e(1359).jpg</path>
  <source>
    <database>Unknown</database>
  </source>
  <size>
    <width>1000</width>
    <height>631</height>
    <depth>3</depth>
  </size>
  <segmented>0</segmented>
  <object>
    <name>fire</name>
    <pose>Unspecified</pose>
    <truncated>0</truncated>
    <difficult>0</difficult>
    <bndbox>
      <xmin>214</xmin>
      <ymin>14</ymin>
      <xmax>689</xmax>
      <ymax>532</ymax>
    </bndbox>
  </object>
</annotation>