<annotation>
	<folder>FireData</folder>
	<filename>Fire_2906.jpg</filename>
	<source>
		<database>The VOC2005 Database</database>
		<annotation>PASCAL VOC2005</annotation>
		<image>flickr</image>
	</source>
	<size>
		<width>4592</width>
		<height>3448</height>
		<depth>3</depth>
	</size>
	<segmented>0</segmented>
	<object>
		<name>fire</name>
		<pose>Unspecified</pose>
		<truncated>0</truncated>
		<difficult>0</difficult>
		<bndbox>
			<xmin>1269</xmin>
			<ymin>451</ymin>
			<xmax>3917</xmax>
			<ymax>3206</ymax>
		</bndbox>
	</object>
</annotation>