<annotation>
	<folder>FireData</folder>
	<filename>Fire_2151.jpg</filename>
	<source>
		<database>The VOC2005 Database</database>
		<annotation>PASCAL VOC2005</annotation>
		<image>flickr</image>
	</source>
	<size>
		<width>400</width>
		<height>256</height>
		<depth>3</depth>
	</size>
	<segmented>0</segmented>
	<object>
		<name>fire</name>
		<pose>Unspecified</pose>
		<truncated>0</truncated>
		<difficult>0</difficult>
		<bndbox>
			<xmin>283</xmin>
			<ymin>62</ymin>
			<xmax>318</xmax>
			<ymax>210</ymax>
		</bndbox>
	</object>
	<object>
		<name>fire</name>
		<pose>Unspecified</pose>
		<truncated>0</truncated>
		<difficult>0</difficult>
		<bndbox>
			<xmin>209</xmin>
			<ymin>166</ymin>
			<xmax>273</xmax>
			<ymax>226</ymax>
		</bndbox>
	</object>
</annotation>