<annotation>
	<folder>FireData</folder>
	<filename>Fire_5298.jpg</filename>
	<source>
		<database>The VOC2005 Database</database>
		<annotation>PASCAL VOC2005</annotation>
		<image>flickr</image>
	</source>
	<size>
		<width>224</width>
		<height>224</height>
		<depth>3</depth>
	</size>
	<segmented>0</segmented>
	<object>
		<name>fire</name>
		<pose>Unspecified</pose>
		<truncated>0</truncated>
		<difficult>0</difficult>
		<bndbox>
			<xmin>127</xmin>
			<ymin>199</ymin>
			<xmax>140</xmax>
			<ymax>211</ymax>
		</bndbox>
	</object>
	<object>
		<name>fire</name>
		<pose>Unspecified</pose>
		<truncated>0</truncated>
		<difficult>0</difficult>
		<bndbox>
			<xmin>169</xmin>
			<ymin>86</ymin>
			<xmax>217</xmax>
			<ymax>121</ymax>
		</bndbox>
	</object>
	<object>
		<name>fire</name>
		<pose>Unspecified</pose>
		<truncated>0</truncated>
		<difficult>0</difficult>
		<bndbox>
			<xmin>146</xmin>
			<ymin>190</ymin>
			<xmax>209</xmax>
			<ymax>201</ymax>
		</bndbox>
	</object>
	<object>
		<name>fire</name>
		<pose>Unspecified</pose>
		<truncated>0</truncated>
		<difficult>0</difficult>
		<bndbox>
			<xmin>87</xmin>
			<ymin>203</ymin>
			<xmax>101</xmax>
			<ymax>211</ymax>
		</bndbox>
	</object>
</annotation>