<annotation>
	<folder>FireData</folder>
	<filename>Fire_6170.jpg</filename>
	<source>
		<database>The VOC2005 Database</database>
		<annotation>PASCAL VOC2005</annotation>
		<image>flickr</image>
	</source>
	<size>
		<width>256</width>
		<height>197</height>
		<depth>3</depth>
	</size>
	<segmented>0</segmented>
	<object>
		<name>fire</name>
		<pose>Unspecified</pose>
		<truncated>0</truncated>
		<difficult>0</difficult>
		<bndbox>
			<xmin>161</xmin>
			<ymin>1</ymin>
			<xmax>174</xmax>
			<ymax>23</ymax>
		</bndbox>
	</object>
	<object>
		<name>fire</name>
		<pose>Unspecified</pose>
		<truncated>0</truncated>
		<difficult>0</difficult>
		<bndbox>
			<xmin>101</xmin>
			<ymin>0</ymin>
			<xmax>112</xmax>
			<ymax>21</ymax>
		</bndbox>
	</object>
	<object>
		<name>fire</name>
		<pose>Unspecified</pose>
		<truncated>0</truncated>
		<difficult>0</difficult>
		<bndbox>
			<xmin>89</xmin>
			<ymin>11</ymin>
			<xmax>102</xmax>
			<ymax>41</ymax>
		</bndbox>
	</object>
	<object>
		<name>fire</name>
		<pose>Unspecified</pose>
		<truncated>0</truncated>
		<difficult>0</difficult>
		<bndbox>
			<xmin>206</xmin>
			<ymin>11</ymin>
			<xmax>218</xmax>
			<ymax>30</ymax>
		</bndbox>
	</object>
</annotation>