<annotation>
	<folder>JPEGImages</folder>
	<filename>000929.jpg</filename>
	<path>G:\data\训练图集\明火\图集叠加\允许漏报（圈的少）\JPEGImages\000929.jpg</path>
	<source>
		<database>Unknown</database>
	</source>
	<size>
		<width>454</width>
		<height>388</height>
		<depth>3</depth>
	</size>
	<segmented>0</segmented>
	<object>
		<name>fire</name>
		<pose>Unspecified</pose>
		<truncated>0</truncated>
		<difficult>0</difficult>
		<bndbox>
			<xmin>39</xmin>
			<ymin>165</ymin>
			<xmax>54</xmax>
			<ymax>209</ymax>
		</bndbox>
	</object>
	<object>
		<name>fire</name>
		<pose>Unspecified</pose>
		<truncated>0</truncated>
		<difficult>0</difficult>
		<bndbox>
			<xmin>53</xmin>
			<ymin>176</ymin>
			<xmax>66</xmax>
			<ymax>189</ymax>
		</bndbox>
	</object>
	<object>
		<name>fire</name>
		<pose>Unspecified</pose>
		<truncated>0</truncated>
		<difficult>0</difficult>
		<bndbox>
			<xmin>58</xmin>
			<ymin>254</ymin>
			<xmax>75</xmax>
			<ymax>268</ymax>
		</bndbox>
	</object>
	<object>
		<name>fire</name>
		<pose>Unspecified</pose>
		<truncated>0</truncated>
		<difficult>0</difficult>
		<bndbox>
			<xmin>17</xmin>
			<ymin>161</ymin>
			<xmax>34</xmax>
			<ymax>187</ymax>
		</bndbox>
	</object>
</annotation>
