<annotation>
	<folder>JPEGImages</folder>
	<filename>00348.jpg</filename>
	<path>G:\data\训练图集\明火\图集叠加\允许漏报（圈的少）\JPEGImages\00348.jpg</path>
	<source>
		<database>Unknown</database>
	</source>
	<size>
		<width>1200</width>
		<height>900</height>
		<depth>3</depth>
	</size>
	<segmented>0</segmented>
	<object>
		<name>fire</name>
		<pose>Unspecified</pose>
		<truncated>0</truncated>
		<difficult>0</difficult>
		<bndbox>
			<xmin>150</xmin>
			<ymin>631</ymin>
			<xmax>229</xmax>
			<ymax>746</ymax>
		</bndbox>
	</object>
	<object>
		<name>fire</name>
		<pose>Unspecified</pose>
		<truncated>0</truncated>
		<difficult>0</difficult>
		<bndbox>
			<xmin>202</xmin>
			<ymin>726</ymin>
			<xmax>256</xmax>
			<ymax>760</ymax>
		</bndbox>
	</object>
	<object>
		<name>fire</name>
		<pose>Unspecified</pose>
		<truncated>0</truncated>
		<difficult>0</difficult>
		<bndbox>
			<xmin>231</xmin>
			<ymin>671</ymin>
			<xmax>274</xmax>
			<ymax>712</ymax>
		</bndbox>
	</object>
	<object>
		<name>fire</name>
		<pose>Unspecified</pose>
		<truncated>0</truncated>
		<difficult>0</difficult>
		<bndbox>
			<xmin>235</xmin>
			<ymin>746</ymin>
			<xmax>301</xmax>
			<ymax>789</ymax>
		</bndbox>
	</object>
	<object>
		<name>fire</name>
		<pose>Unspecified</pose>
		<truncated>0</truncated>
		<difficult>0</difficult>
		<bndbox>
			<xmin>309</xmin>
			<ymin>677</ymin>
			<xmax>351</xmax>
			<ymax>739</ymax>
		</bndbox>
	</object>
	<object>
		<name>fire</name>
		<pose>Unspecified</pose>
		<truncated>0</truncated>
		<difficult>0</difficult>
		<bndbox>
			<xmin>312</xmin>
			<ymin>738</ymin>
			<xmax>416</xmax>
			<ymax>790</ymax>
		</bndbox>
	</object>
	<object>
		<name>fire</name>
		<pose>Unspecified</pose>
		<truncated>0</truncated>
		<difficult>0</difficult>
		<bndbox>
			<xmin>417</xmin>
			<ymin>729</ymin>
			<xmax>461</xmax>
			<ymax>781</ymax>
		</bndbox>
	</object>
	<object>
		<name>fire</name>
		<pose>Unspecified</pose>
		<truncated>0</truncated>
		<difficult>0</difficult>
		<bndbox>
			<xmin>465</xmin>
			<ymin>708</ymin>
			<xmax>499</xmax>
			<ymax>762</ymax>
		</bndbox>
	</object>
	<object>
		<name>fire</name>
		<pose>Unspecified</pose>
		<truncated>0</truncated>
		<difficult>0</difficult>
		<bndbox>
			<xmin>495</xmin>
			<ymin>682</ymin>
			<xmax>539</xmax>
			<ymax>759</ymax>
		</bndbox>
	</object>
	<object>
		<name>fire</name>
		<pose>Unspecified</pose>
		<truncated>0</truncated>
		<difficult>0</difficult>
		<bndbox>
			<xmin>553</xmin>
			<ymin>703</ymin>
			<xmax>584</xmax>
			<ymax>746</ymax>
		</bndbox>
	</object>
	<object>
		<name>fire</name>
		<pose>Unspecified</pose>
		<truncated>0</truncated>
		<difficult>0</difficult>
		<bndbox>
			<xmin>584</xmin>
			<ymin>671</ymin>
			<xmax>613</xmax>
			<ymax>709</ymax>
		</bndbox>
	</object>
	<object>
		<name>fire</name>
		<pose>Unspecified</pose>
		<truncated>0</truncated>
		<difficult>0</difficult>
		<bndbox>
			<xmin>595</xmin>
			<ymin>709</ymin>
			<xmax>634</xmax>
			<ymax>749</ymax>
		</bndbox>
	</object>
	<object>
		<name>fire</name>
		<pose>Unspecified</pose>
		<truncated>0</truncated>
		<difficult>0</difficult>
		<bndbox>
			<xmin>633</xmin>
			<ymin>725</ymin>
			<xmax>672</xmax>
			<ymax>752</ymax>
		</bndbox>
	</object>
	<object>
		<name>fire</name>
		<pose>Unspecified</pose>
		<truncated>0</truncated>
		<difficult>0</difficult>
		<bndbox>
			<xmin>682</xmin>
			<ymin>711</ymin>
			<xmax>700</xmax>
			<ymax>734</ymax>
		</bndbox>
	</object>
	<object>
		<name>fire</name>
		<pose>Unspecified</pose>
		<truncated>0</truncated>
		<difficult>0</difficult>
		<bndbox>
			<xmin>697</xmin>
			<ymin>734</ymin>
			<xmax>726</xmax>
			<ymax>755</ymax>
		</bndbox>
	</object>
	<object>
		<name>fire</name>
		<pose>Unspecified</pose>
		<truncated>0</truncated>
		<difficult>0</difficult>
		<bndbox>
			<xmin>747</xmin>
			<ymin>709</ymin>
			<xmax>772</xmax>
			<ymax>766</ymax>
		</bndbox>
	</object>
	<object>
		<name>fire</name>
		<pose>Unspecified</pose>
		<truncated>0</truncated>
		<difficult>0</difficult>
		<bndbox>
			<xmin>775</xmin>
			<ymin>682</ymin>
			<xmax>799</xmax>
			<ymax>751</ymax>
		</bndbox>
	</object>
	<object>
		<name>fire</name>
		<pose>Unspecified</pose>
		<truncated>0</truncated>
		<difficult>0</difficult>
		<bndbox>
			<xmin>801</xmin>
			<ymin>721</ymin>
			<xmax>823</xmax>
			<ymax>760</ymax>
		</bndbox>
	</object>
	<object>
		<name>fire</name>
		<pose>Unspecified</pose>
		<truncated>0</truncated>
		<difficult>0</difficult>
		<bndbox>
			<xmin>817</xmin>
			<ymin>736</ymin>
			<xmax>847</xmax>
			<ymax>757</ymax>
		</bndbox>
	</object>
	<object>
		<name>fire</name>
		<pose>Unspecified</pose>
		<truncated>0</truncated>
		<difficult>0</difficult>
		<bndbox>
			<xmin>879</xmin>
			<ymin>749</ymin>
			<xmax>906</xmax>
			<ymax>783</ymax>
		</bndbox>
	</object>
	<object>
		<name>fire</name>
		<pose>Unspecified</pose>
		<truncated>0</truncated>
		<difficult>0</difficult>
		<bndbox>
			<xmin>921</xmin>
			<ymin>743</ymin>
			<xmax>963</xmax>
			<ymax>786</ymax>
		</bndbox>
	</object>
	<object>
		<name>fire</name>
		<pose>Unspecified</pose>
		<truncated>0</truncated>
		<difficult>0</difficult>
		<bndbox>
			<xmin>970</xmin>
			<ymin>739</ymin>
			<xmax>1022</xmax>
			<ymax>788</ymax>
		</bndbox>
	</object>
	<object>
		<name>fire</name>
		<pose>Unspecified</pose>
		<truncated>0</truncated>
		<difficult>0</difficult>
		<bndbox>
			<xmin>1041</xmin>
			<ymin>776</ymin>
			<xmax>1082</xmax>
			<ymax>808</ymax>
		</bndbox>
	</object>
	<object>
		<name>fire</name>
		<pose>Unspecified</pose>
		<truncated>0</truncated>
		<difficult>0</difficult>
		<bndbox>
			<xmin>1105</xmin>
			<ymin>746</ymin>
			<xmax>1131</xmax>
			<ymax>789</ymax>
		</bndbox>
	</object>
	<object>
		<name>fire</name>
		<pose>Unspecified</pose>
		<truncated>0</truncated>
		<difficult>0</difficult>
		<bndbox>
			<xmin>1092</xmin>
			<ymin>769</ymin>
			<xmax>1112</xmax>
			<ymax>806</ymax>
		</bndbox>
	</object>
</annotation>
