<annotation>
	<folder>JPEGImages</folder>
	<filename>fire_150.jpg</filename>
	<path>G:\data\训练图集\烟雾\图集叠加\JPEGImages\fire_150.jpg</path>
	<source>
		<database>Unknown</database>
	</source>
	<size>
		<width>496</width>
		<height>280</height>
		<depth>3</depth>
	</size>
	<segmented>0</segmented>
	<object>
		<name>smoke</name>
		<pose>Unspecified</pose>
		<truncated>1</truncated>
		<difficult>0</difficult>
		<bndbox>
			<xmin>51</xmin>
			<ymin>1</ymin>
			<xmax>257</xmax>
			<ymax>45</ymax>
		</bndbox>
	</object>
	<object>
		<name>smoke</name>
		<pose>Unspecified</pose>
		<truncated>0</truncated>
		<difficult>0</difficult>
		<bndbox>
			<xmin>86</xmin>
			<ymin>46</ymin>
			<xmax>317</xmax>
			<ymax>81</ymax>
		</bndbox>
	</object>
	<object>
		<name>smoke</name>
		<pose>Unspecified</pose>
		<truncated>0</truncated>
		<difficult>0</difficult>
		<bndbox>
			<xmin>98</xmin>
			<ymin>81</ymin>
			<xmax>149</xmax>
			<ymax>154</ymax>
		</bndbox>
	</object>
	<object>
		<name>smoke</name>
		<pose>Unspecified</pose>
		<truncated>0</truncated>
		<difficult>0</difficult>
		<bndbox>
			<xmin>153</xmin>
			<ymin>83</ymin>
			<xmax>210</xmax>
			<ymax>165</ymax>
		</bndbox>
	</object>
</annotation>
