<annotation>
	<folder>VOC2005</folder>
	<filename>001574.jpg</filename>
	<source>
		<database>The VOC2019 Database</database>
		<annotation>PASCAL VOC2019</annotation>
		<image>flickr</image>
	</source>
	<size>
		<width>624</width>
		<height>991</height>
		<depth>3</depth>
	</size>
	<segmented>0</segmented>
	<object>
		<name>smoke</name>
		<pose>Unspecified</pose>
		<truncated>0</truncated>
		<difficult>0</difficult>
		<bndbox>
			<xmin>471</xmin>
			<ymin>91</ymin>
			<xmax>615</xmax>
			<ymax>282</ymax>
		</bndbox>
	</object>
	<object>
		<name>smoke</name>
		<pose>Unspecified</pose>
		<truncated>0</truncated>
		<difficult>0</difficult>
		<bndbox>
			<xmin>152</xmin>
			<ymin>134</ymin>
			<xmax>293</xmax>
			<ymax>276</ymax>
		</bndbox>
	</object>
	<object>
		<name>smoke</name>
		<pose>Unspecified</pose>
		<truncated>0</truncated>
		<difficult>0</difficult>
		<bndbox>
			<xmin>205</xmin>
			<ymin>317</ymin>
			<xmax>371</xmax>
			<ymax>429</ymax>
		</bndbox>
	</object>
</annotation>
