<annotation>
	<folder>JPEGImages</folder>
	<filename>00504.jpg</filename>
	<path>G:\data\训练图集\烟雾\图集叠加\允许漏报（圈的少）\JPEGImages\00504.jpg</path>
	<source>
		<database>Unknown</database>
	</source>
	<size>
		<width>950</width>
		<height>631</height>
		<depth>3</depth>
	</size>
	<segmented>0</segmented>
	<object>
		<name>smoke</name>
		<pose>Unspecified</pose>
		<truncated>0</truncated>
		<difficult>0</difficult>
		<bndbox>
			<xmin>343</xmin>
			<ymin>5</ymin>
			<xmax>511</xmax>
			<ymax>99</ymax>
		</bndbox>
	</object>
	<object>
		<name>smoke</name>
		<pose>Unspecified</pose>
		<truncated>0</truncated>
		<difficult>0</difficult>
		<bndbox>
			<xmin>521</xmin>
			<ymin>3</ymin>
			<xmax>728</xmax>
			<ymax>124</ymax>
		</bndbox>
	</object>
	<object>
		<name>smoke</name>
		<pose>Unspecified</pose>
		<truncated>0</truncated>
		<difficult>0</difficult>
		<bndbox>
			<xmin>598</xmin>
			<ymin>134</ymin>
			<xmax>744</xmax>
			<ymax>274</ymax>
		</bndbox>
	</object>
	<object>
		<name>smoke</name>
		<pose>Unspecified</pose>
		<truncated>0</truncated>
		<difficult>0</difficult>
		<bndbox>
			<xmin>307</xmin>
			<ymin>327</ymin>
			<xmax>395</xmax>
			<ymax>379</ymax>
		</bndbox>
	</object>
	<object>
		<name>smoke</name>
		<pose>Unspecified</pose>
		<truncated>0</truncated>
		<difficult>0</difficult>
		<bndbox>
			<xmin>268</xmin>
			<ymin>229</ymin>
			<xmax>405</xmax>
			<ymax>285</ymax>
		</bndbox>
	</object>
	<object>
		<name>smoke</name>
		<pose>Unspecified</pose>
		<truncated>0</truncated>
		<difficult>0</difficult>
		<bndbox>
			<xmin>502</xmin>
			<ymin>129</ymin>
			<xmax>589</xmax>
			<ymax>188</ymax>
		</bndbox>
	</object>
	<object>
		<name>smoke</name>
		<pose>Unspecified</pose>
		<truncated>0</truncated>
		<difficult>0</difficult>
		<bndbox>
			<xmin>265</xmin>
			<ymin>474</ymin>
			<xmax>349</xmax>
			<ymax>558</ymax>
		</bndbox>
	</object>
</annotation>
