<annotation>
	<folder>JPEGImages</folder>
	<filename>fire_220.jpg</filename>
	<path>G:\data\训练图集\烟雾\图集叠加\JPEGImages\fire_220.jpg</path>
	<source>
		<database>Unknown</database>
	</source>
	<size>
		<width>400</width>
		<height>300</height>
		<depth>3</depth>
	</size>
	<segmented>0</segmented>
	<object>
		<name>smoke</name>
		<pose>Unspecified</pose>
		<truncated>0</truncated>
		<difficult>0</difficult>
		<bndbox>
			<xmin>205</xmin>
			<ymin>6</ymin>
			<xmax>343</xmax>
			<ymax>43</ymax>
		</bndbox>
	</object>
	<object>
		<name>smoke</name>
		<pose>Unspecified</pose>
		<truncated>0</truncated>
		<difficult>0</difficult>
		<bndbox>
			<xmin>207</xmin>
			<ymin>45</ymin>
			<xmax>285</xmax>
			<ymax>77</ymax>
		</bndbox>
	</object>
</annotation>
