<annotation>
	<folder>VOC2005</folder>
	<filename>01257.jpg</filename>
	<source>
		<database>The VOC2019 Database</database>
		<annotation>PASCAL VOC2019</annotation>
		<image>flickr</image>
	</source>
	<size>
		<width>559</width>
		<height>292</height>
		<depth>3</depth>
	</size>
	<segmented>0</segmented>
	<object>
		<name>smoke</name>
		<pose>Unspecified</pose>
		<truncated>0</truncated>
		<difficult>0</difficult>
		<bndbox>
			<xmin>4</xmin>
			<ymin>2</ymin>
			<xmax>475</xmax>
			<ymax>160</ymax>
		</bndbox>
	</object>
	<object>
		<name>smoke</name>
		<pose>Unspecified</pose>
		<truncated>0</truncated>
		<difficult>0</difficult>
		<bndbox>
			<xmin>230</xmin>
			<ymin>158</ymin>
			<xmax>317</xmax>
			<ymax>219</ymax>
		</bndbox>
	</object>
	<object>
		<name>smoke</name>
		<pose>Unspecified</pose>
		<truncated>0</truncated>
		<difficult>0</difficult>
		<bndbox>
			<xmin>333</xmin>
			<ymin>157</ymin>
			<xmax>422</xmax>
			<ymax>194</ymax>
		</bndbox>
	</object>
</annotation>
