<annotation>
	<folder>VOC2005</folder>
	<filename>01085.jpg</filename>
	<source>
		<database>The VOC2019 Database</database>
		<annotation>PASCAL VOC2019</annotation>
		<image>flickr</image>
	</source>
	<size>
		<width>550</width>
		<height>440</height>
		<depth>3</depth>
	</size>
	<segmented>0</segmented>
	<object>
		<name>smoke</name>
		<pose>Unspecified</pose>
		<truncated>0</truncated>
		<difficult>0</difficult>
		<bndbox>
			<xmin>4</xmin>
			<ymin>2</ymin>
			<xmax>354</xmax>
			<ymax>183</ymax>
		</bndbox>
	</object>
	<object>
		<name>smoke</name>
		<pose>Unspecified</pose>
		<truncated>0</truncated>
		<difficult>0</difficult>
		<bndbox>
			<xmin>36</xmin>
			<ymin>185</ymin>
			<xmax>355</xmax>
			<ymax>291</ymax>
		</bndbox>
	</object>
	<object>
		<name>smoke</name>
		<pose>Unspecified</pose>
		<truncated>0</truncated>
		<difficult>0</difficult>
		<bndbox>
			<xmin>257</xmin>
			<ymin>292</ymin>
			<xmax>424</xmax>
			<ymax>350</ymax>
		</bndbox>
	</object>
</annotation>
