<annotation>
	<folder>JPEGImages</folder>
	<filename>001439.jpg</filename>
	<path>G:\data\训练图集\烟雾\图集叠加\允许漏报（圈的少）\JPEGImages\001439.jpg</path>
	<source>
		<database>Unknown</database>
	</source>
	<size>
		<width>1920</width>
		<height>1080</height>
		<depth>3</depth>
	</size>
	<segmented>0</segmented>
	<object>
		<name>smoke</name>
		<pose>Unspecified</pose>
		<truncated>0</truncated>
		<difficult>0</difficult>
		<bndbox>
			<xmin>585</xmin>
			<ymin>559</ymin>
			<xmax>765</xmax>
			<ymax>639</ymax>
		</bndbox>
	</object>
	<object>
		<name>smoke</name>
		<pose>Unspecified</pose>
		<truncated>0</truncated>
		<difficult>0</difficult>
		<bndbox>
			<xmin>679</xmin>
			<ymin>445</ymin>
			<xmax>905</xmax>
			<ymax>561</ymax>
		</bndbox>
	</object>
	<object>
		<name>smoke</name>
		<pose>Unspecified</pose>
		<truncated>0</truncated>
		<difficult>0</difficult>
		<bndbox>
			<xmin>805</xmin>
			<ymin>343</ymin>
			<xmax>916</xmax>
			<ymax>441</ymax>
		</bndbox>
	</object>
	<object>
		<name>smoke</name>
		<pose>Unspecified</pose>
		<truncated>0</truncated>
		<difficult>0</difficult>
		<bndbox>
			<xmin>919</xmin>
			<ymin>225</ymin>
			<xmax>1241</xmax>
			<ymax>398</ymax>
		</bndbox>
	</object>
	<object>
		<name>smoke</name>
		<pose>Unspecified</pose>
		<truncated>1</truncated>
		<difficult>0</difficult>
		<bndbox>
			<xmin>1241</xmin>
			<ymin>1</ymin>
			<xmax>1481</xmax>
			<ymax>439</ymax>
		</bndbox>
	</object>
	<object>
		<name>smoke</name>
		<pose>Unspecified</pose>
		<truncated>0</truncated>
		<difficult>0</difficult>
		<bndbox>
			<xmin>929</xmin>
			<ymin>403</ymin>
			<xmax>1128</xmax>
			<ymax>568</ymax>
		</bndbox>
	</object>
	<object>
		<name>smoke</name>
		<pose>Unspecified</pose>
		<truncated>0</truncated>
		<difficult>0</difficult>
		<bndbox>
			<xmin>1457</xmin>
			<ymin>113</ymin>
			<xmax>1689</xmax>
			<ymax>453</ymax>
		</bndbox>
	</object>
</annotation>
